syn.utils-0.0.1-nspkg.pth
tests/__init__.py
tests/cmdargs/__init__.py
tests/cmdargs/test_args.py
syn/utils/__init__.py
syn/utils/cmdargs/__init__.py
syn/utils/cmdargs/args.py
syn.utils-0.0.1.dist-info/namespace_packages.txt
syn.utils-0.0.1.dist-info/RECORD
syn.utils-0.0.1.dist-info/metadata.json
syn.utils-0.0.1.dist-info/METADATA
syn.utils-0.0.1.dist-info/DESCRIPTION.rst
syn.utils-0.0.1.dist-info/top_level.txt
syn.utils-0.0.1.dist-info/WHEEL
